vectogebra/__init__.py
vectogebra/geometry.py
vectogebra/utilities.py
vectogebra/vector.py
vectogebra-0.0.10.dist-info/LICENSE
vectogebra-0.0.10.dist-info/METADATA
vectogebra-0.0.10.dist-info/WHEEL
vectogebra-0.0.10.dist-info/top_level.txt
vectogebra-0.0.10.dist-info/RECORD
