Metadata-Version: 2.1
Name: vectogebra
Version: 0.0.10
Summary: Package that helps you work with vector algebra !
Home-page: https://github.com/maasir554/vectogebra
Author: Mohammad Maasir
Author-email: maasir554@gmail.com
License: MIT
Project-URL: Bug Tracker, https://github.com/maasir554/vectogebra/issues
Classifier: Programming Language :: Python :: 3
Classifier: License :: OSI Approved :: MIT License
Classifier: Operating System :: OS Independent
Requires-Python: >=3.6
License-File: LICENSE
